mvdosint/__init__.py
mvdosint/mvd.py
MVDOSINT-0.1.dist-info/METADATA
MVDOSINT-0.1.dist-info/WHEEL
MVDOSINT-0.1.dist-info/entry_points.txt
MVDOSINT-0.1.dist-info/top_level.txt
MVDOSINT-0.1.dist-info/RECORD
